[
    {
        "id": 5,
        "text": "Hello Angular4pro.com",
        "link": "https://angular4pro.com",
        "snippet": " <h2 style=\"color:red;\">Helo world</h2><p><center>I am in center</center></p>",
        "category": " AngularJS, AngularJS 1.x",
        "tags": " Tutorials"
    },
    {
        "id": 7,
        "text": "Welcome to Angular4pro.com",
        "link": "https://angular4pro.com",
        "snippet": "<div> <h2>Welcome to Angular4pro.com</h2><p>hello</p> </div>",
        "category": " AngularJS, AngularJS 1.x",
        "tags": " Tutorials"
    },
    {
      "id": 105,
      "text": "AngularJS Number Expression",
      "link": "https://angular4pro.com/number-expressions-angularjs.html",
      "snippet": "<body><div ng-app><p> Addition of 2 + 3 = {{ 2 + 3 }}</p></div> </body>",
      "category": " AngularJS, AngularJS 1.x",
      "tags": " Tutorials, AngularJs Expression"
    },
     {
      "id": 106,
      "text": "AngularJS Number Expression",
      "link": "https://angular4pro.com/number-expressions-angularjs.html",
      "snippet": "<body><div ng-app><p> Multiplication of 10 * 10 =  <span ng-bind="10 * 10"></span> </p></div> </body>",
      "category": " AngularJS, AngularJS 1.x",
      "tags": " Tutorials, AngularJs Expression"
    }
    
]

